pytest_selfie/SelfieSettingsAPI.py
pytest_selfie/__init__.py
pytest_selfie/plugin.py
pytest_selfie-1.0.0.dist-info/METADATA
pytest_selfie-1.0.0.dist-info/WHEEL
pytest_selfie-1.0.0.dist-info/entry_points.txt
pytest_selfie-1.0.0.dist-info/top_level.txt
pytest_selfie-1.0.0.dist-info/RECORD
