Metadata-Version: 2.1
Name: pytest-selfie
Version: 1.0.0
Summary: A pytest plugin for selfie snapshot testing.
Author-email: Edwin Ye <EdwinYeDeveloper@gmail.com>, Harvir Sahota <hsahota2312@gmail.com>, Ned Twigg <ned.twigg@diffplug.com>, Selina Delgado <sdelgado411@gmail.com>
License: Apache-2.0
Requires-Python: >=3.9
Requires-Dist: pytest>=8.0.0
Requires-Dist: selfie-lib
